HISTORY.txt
README.txt
setup.cfg
setup.py
prdg/__init__.py
prdg.ploneio.egg-info/PKG-INFO
prdg.ploneio.egg-info/SOURCES.txt
prdg.ploneio.egg-info/dependency_links.txt
prdg.ploneio.egg-info/namespace_packages.txt
prdg.ploneio.egg-info/not-zip-safe
prdg.ploneio.egg-info/requires.txt
prdg.ploneio.egg-info/top_level.txt
prdg/ploneio/README.txt
prdg/ploneio/__init__.py
prdg/ploneio/config.py
prdg/ploneio/configure.zcml
prdg/ploneio/context.py
prdg/ploneio/export.py
prdg/ploneio/load.py
prdg/ploneio/browser/__init__.py
prdg/ploneio/browser/base.py
prdg/ploneio/browser/configure.zcml
prdg/ploneio/browser/export.py
prdg/ploneio/browser/load.py
prdg/ploneio/interfaces/__init__.py
prdg/ploneio/interfaces/base.py
prdg/ploneio/interfaces/export.py
prdg/ploneio/interfaces/load.py
prdg/ploneio/tests/__init__.py
prdg/ploneio/tests/base.py
prdg/ploneio/tests/test_doc.py