Metadata-Version: 1.0
Name: prdg.ploneio
Version: 0.0.2
Summary: Provide a set of views allowing to import and export content into and from a Plone Site.
Home-page: http://code.google.com/p/prdg-python/
Author: Rafael Oliveira
Author-email: rafaelbco@gmail.com
License: GPL
Platform: UNKNOWN
Classifier: Framework :: Plone
Classifier: Programming Language :: Python
Classifier: Topic :: Software Development :: Libraries :: Python Modules
